tkitDb/__init__.py
tkitDb/db.py
tkitDb/litDb.py
tkitDb/pkl.py
tkitDb-0.0.1.320220108150357.dist-info/LICENSE
tkitDb-0.0.1.320220108150357.dist-info/METADATA
tkitDb-0.0.1.320220108150357.dist-info/WHEEL
tkitDb-0.0.1.320220108150357.dist-info/top_level.txt
tkitDb-0.0.1.320220108150357.dist-info/RECORD
