Metadata-Version: 2.1
Name: tkitDb
Version: 0.0.1.320220108150357
Summary: Terry toolkit db
Home-page: https://terry-toolkit.terrychan.org/zh/master/
Author: Terry Chan
Author-email: napoler2008@gmail.com
License: UNKNOWN
Platform: UNKNOWN
Requires-Dist: tqdm (==4.38.0)
Requires-Dist: unqlite (==0.7.1)
Requires-Dist: sqlitedict (==1.7.0)
